py21cmcast/__init__.py
py21cmcast/__main__.py
py21cmcast/core.py
py21cmcast/experiments.py
py21cmcast/power.py
py21cmcast/runs.py
py21cmcast/tools.py
py21cmcast-1.0.4.dist-info/LICENSE
py21cmcast-1.0.4.dist-info/METADATA
py21cmcast-1.0.4.dist-info/WHEEL
py21cmcast-1.0.4.dist-info/top_level.txt
py21cmcast-1.0.4.dist-info/RECORD
