Metadata-Version: 2.1
Name: py21cmcast
Version: 1.0.4
Summary: Fisher forecasts with 21cm experiments
Author-email: Gaétan Facchinetti <gaetanfacc@gmail.com>
License: GNU GENERAL PUBLIC LICENSE
Project-URL: Homepage, https://github.com/gaetanfacchinetti/21cmCAST
Keywords: 21cm,fisher,statistics,cosmology
Classifier: License :: OSI Approved :: GNU General Public License v3 (GPLv3)
Classifier: Programming Language :: Python
Classifier: Programming Language :: Python :: 3
Classifier: Operating System :: Unix
Classifier: Operating System :: MacOS :: MacOS X
Classifier: Operating System :: Microsoft :: Windows
Requires-Python: >=3.6
License-File: LICENSE
Requires-Dist: numpy >=1.16.5
Requires-Dist: matplotlib >=3.4.3
Requires-Dist: powerbox >=0.7.3
Requires-Dist: configparser >=6.0.0
Requires-Dist: astropy >=5.0.0
Requires-Dist: scipy
Provides-Extra: dev
Requires-Dist: 21cmSense >=2.0.0 ; extra == 'dev'
Requires-Dist: 21cmfast >=3.0.0 ; extra == 'dev'
